{
  "annotations": {
    "list": [
      {
        "builtIn": 1,
        "datasource": { "type": "grafana", "uid": "-- Grafana --" },
        "enable": true,
        "hide": true,
        "iconColor": "rgba(0, 211, 255, 1)",
        "name": "Annotations & Alerts",
        "type": "dashboard"
      }
    ]
  },
  "description": "ZTE MC801A 5G/LTE signal quality, connection drops, temperature and throughput.",
  "editable": true,
  "fiscalYearStartMonth": 0,
  "graphTooltip": 1,
  "id": null,
  "links": [],
  "panels": [
    {
      "id": 1,
      "title": "Connection",
      "type": "stat",
      "gridPos": { "h": 4, "w": 4, "x": 0, "y": 0 },
      "datasource": { "type": "prometheus", "uid": "cellsentry-prometheus" },
      "targets": [
        {
          "expr": "cellsentry_connection_up",
          "legendFormat": "__auto",
          "instant": true,
          "refId": "A"
        }
      ],
      "options": {
        "reduceOptions": { "values": false, "calcs": ["lastNotNull"], "fields": "" },
        "orientation": "auto",
        "textMode": "auto",
        "colorMode": "background",
        "graphMode": "none",
        "justifyMode": "center"
      },
      "fieldConfig": {
        "defaults": {
          "mappings": [
            {
              "type": "value",
              "options": {
                "0": { "text": "Disconnected", "color": "red",   "index": 0 },
                "1": { "text": "Connected",    "color": "green", "index": 1 }
              }
            }
          ],
          "thresholds": {
            "mode": "absolute",
            "steps": [
              { "color": "red",   "value": null },
              { "color": "green", "value": 1 }
            ]
          }
        },
        "overrides": []
      }
    },
    {
      "id": 2,
      "title": "Signal Bars",
      "type": "gauge",
      "gridPos": { "h": 4, "w": 4, "x": 4, "y": 0 },
      "datasource": { "type": "prometheus", "uid": "cellsentry-prometheus" },
      "targets": [
        {
          "expr": "cellsentry_signal_bars",
          "legendFormat": "__auto",
          "instant": true,
          "refId": "A"
        }
      ],
      "options": {
        "reduceOptions": { "values": false, "calcs": ["lastNotNull"], "fields": "" },
        "orientation": "auto",
        "showThresholdLabels": false,
        "showThresholdMarkers": true
      },
      "fieldConfig": {
        "defaults": {
          "min": 0,
          "max": 5,
          "thresholds": {
            "mode": "absolute",
            "steps": [
              { "color": "red",    "value": null },
              { "color": "orange", "value": 2 },
              { "color": "yellow", "value": 3 },
              { "color": "green",  "value": 4 }
            ]
          }
        },
        "overrides": []
      }
    },
    {
      "id": 3,
      "title": "Connection Drops",
      "type": "stat",
      "gridPos": { "h": 4, "w": 4, "x": 8, "y": 0 },
      "datasource": { "type": "prometheus", "uid": "cellsentry-prometheus" },
      "targets": [
        {
          "expr": "cellsentry_connection_drops_total",
          "legendFormat": "__auto",
          "instant": true,
          "refId": "A"
        }
      ],
      "options": {
        "reduceOptions": { "values": false, "calcs": ["lastNotNull"], "fields": "" },
        "orientation": "auto",
        "textMode": "auto",
        "colorMode": "background",
        "graphMode": "none",
        "justifyMode": "center"
      },
      "fieldConfig": {
        "defaults": {
          "thresholds": {
            "mode": "absolute",
            "steps": [
              { "color": "green",  "value": null },
              { "color": "yellow", "value": 1 },
              { "color": "red",    "value": 5 }
            ]
          }
        },
        "overrides": []
      }
    },
    {
      "id": 4,
      "title": "Scrape Health",
      "type": "stat",
      "gridPos": { "h": 4, "w": 4, "x": 12, "y": 0 },
      "datasource": { "type": "prometheus", "uid": "cellsentry-prometheus" },
      "targets": [
        {
          "expr": "cellsentry_scrape_success",
          "legendFormat": "__auto",
          "instant": true,
          "refId": "A"
        }
      ],
      "options": {
        "reduceOptions": { "values": false, "calcs": ["lastNotNull"], "fields": "" },
        "orientation": "auto",
        "textMode": "auto",
        "colorMode": "background",
        "graphMode": "none",
        "justifyMode": "center"
      },
      "fieldConfig": {
        "defaults": {
          "mappings": [
            {
              "type": "value",
              "options": {
                "0": { "text": "Failed", "color": "red",   "index": 0 },
                "1": { "text": "OK",     "color": "green", "index": 1 }
              }
            }
          ],
          "thresholds": {
            "mode": "absolute",
            "steps": [
              { "color": "red",   "value": null },
              { "color": "green", "value": 1 }
            ]
          }
        },
        "overrides": []
      }
    },
    {
      "id": 5,
      "title": "Temp — LTE Modem",
      "type": "stat",
      "gridPos": { "h": 4, "w": 4, "x": 16, "y": 0 },
      "datasource": { "type": "prometheus", "uid": "cellsentry-prometheus" },
      "targets": [
        {
          "expr": "cellsentry_temperature_celsius{sensor=\"lte\"}",
          "legendFormat": "LTE",
          "instant": true,
          "refId": "A"
        }
      ],
      "options": {
        "reduceOptions": { "values": false, "calcs": ["lastNotNull"], "fields": "" },
        "orientation": "auto",
        "textMode": "auto",
        "colorMode": "background",
        "graphMode": "none",
        "justifyMode": "center"
      },
      "fieldConfig": {
        "defaults": {
          "unit": "celsius",
          "thresholds": {
            "mode": "absolute",
            "steps": [
              { "color": "green",  "value": null },
              { "color": "yellow", "value": 60 },
              { "color": "red",    "value": 75 }
            ]
          }
        },
        "overrides": []
      }
    },
    {
      "id": 6,
      "title": "Temp — 5G Modem",
      "type": "stat",
      "gridPos": { "h": 4, "w": 4, "x": 20, "y": 0 },
      "datasource": { "type": "prometheus", "uid": "cellsentry-prometheus" },
      "targets": [
        {
          "expr": "cellsentry_temperature_celsius{sensor=\"5g\"}",
          "legendFormat": "5G",
          "instant": true,
          "refId": "A"
        }
      ],
      "options": {
        "reduceOptions": { "values": false, "calcs": ["lastNotNull"], "fields": "" },
        "orientation": "auto",
        "textMode": "auto",
        "colorMode": "background",
        "graphMode": "none",
        "justifyMode": "center"
      },
      "fieldConfig": {
        "defaults": {
          "unit": "celsius",
          "thresholds": {
            "mode": "absolute",
            "steps": [
              { "color": "green",  "value": null },
              { "color": "yellow", "value": 60 },
              { "color": "red",    "value": 75 }
            ]
          }
        },
        "overrides": []
      }
    },
    {
      "id": 10,
      "title": "Network Type",
      "type": "stat",
      "gridPos": { "h": 4, "w": 4, "x": 0, "y": 4 },
      "datasource": { "type": "prometheus", "uid": "cellsentry-prometheus" },
      "targets": [
        {
          "expr": "cellsentry_modem_info",
          "legendFormat": "{{network_type}}",
          "instant": true,
          "refId": "A"
        }
      ],
      "options": {
        "reduceOptions": { "values": false, "calcs": ["lastNotNull"], "fields": "" },
        "orientation": "auto",
        "textMode": "name",
        "colorMode": "none",
        "graphMode": "none",
        "justifyMode": "center"
      },
      "fieldConfig": { "defaults": {}, "overrides": [] }
    },
    {
      "id": 11,
      "title": "LTE Band",
      "type": "stat",
      "gridPos": { "h": 4, "w": 4, "x": 4, "y": 4 },
      "datasource": { "type": "prometheus", "uid": "cellsentry-prometheus" },
      "targets": [
        {
          "expr": "cellsentry_modem_info",
          "legendFormat": "B{{band_lte}}",
          "instant": true,
          "refId": "A"
        }
      ],
      "options": {
        "reduceOptions": { "values": false, "calcs": ["lastNotNull"], "fields": "" },
        "orientation": "auto",
        "textMode": "name",
        "colorMode": "none",
        "graphMode": "none",
        "justifyMode": "center"
      },
      "fieldConfig": { "defaults": {}, "overrides": [] }
    },
    {
      "id": 12,
      "title": "LTE PCI (decimal)",
      "type": "stat",
      "gridPos": { "h": 4, "w": 4, "x": 8, "y": 4 },
      "datasource": { "type": "prometheus", "uid": "cellsentry-prometheus" },
      "targets": [
        {
          "expr": "cellsentry_cell_decoded_info",
          "legendFormat": "{{pci_lte_dec}}",
          "instant": true,
          "refId": "A"
        }
      ],
      "options": {
        "reduceOptions": { "values": false, "calcs": ["lastNotNull"], "fields": "" },
        "orientation": "auto",
        "textMode": "name",
        "colorMode": "none",
        "graphMode": "none",
        "justifyMode": "center"
      },
      "fieldConfig": { "defaults": {}, "overrides": [] }
    },
    {
      "id": 13,
      "title": "Cell ID (decimal)",
      "type": "stat",
      "gridPos": { "h": 4, "w": 4, "x": 12, "y": 4 },
      "datasource": { "type": "prometheus", "uid": "cellsentry-prometheus" },
      "targets": [
        {
          "expr": "cellsentry_cell_decoded_info",
          "legendFormat": "{{cell_id_dec}}",
          "instant": true,
          "refId": "A"
        }
      ],
      "options": {
        "reduceOptions": { "values": false, "calcs": ["lastNotNull"], "fields": "" },
        "orientation": "auto",
        "textMode": "name",
        "colorMode": "none",
        "graphMode": "none",
        "justifyMode": "center"
      },
      "fieldConfig": { "defaults": {}, "overrides": [] }
    },
    {
      "id": 16,
      "title": "eNB ID (base station)",
      "type": "stat",
      "gridPos": { "h": 4, "w": 4, "x": 16, "y": 4 },
      "datasource": { "type": "prometheus", "uid": "cellsentry-prometheus" },
      "targets": [
        {
          "expr": "cellsentry_cell_decoded_info",
          "legendFormat": "{{enb_id}} / sector {{sector}}",
          "instant": true,
          "refId": "A"
        }
      ],
      "options": {
        "reduceOptions": { "values": false, "calcs": ["lastNotNull"], "fields": "" },
        "orientation": "auto",
        "textMode": "name",
        "colorMode": "none",
        "graphMode": "none",
        "justifyMode": "center"
      },
      "fieldConfig": { "defaults": {}, "overrides": [] }
    },
    {
      "id": 17,
      "title": "TAC (LAC for OpenCelliD)",
      "type": "stat",
      "gridPos": { "h": 4, "w": 4, "x": 20, "y": 4 },
      "datasource": { "type": "prometheus", "uid": "cellsentry-prometheus" },
      "targets": [
        {
          "expr": "cellsentry_cell_decoded_info",
          "legendFormat": "{{tac}}",
          "instant": true,
          "refId": "A"
        }
      ],
      "options": {
        "reduceOptions": { "values": false, "calcs": ["lastNotNull"], "fields": "" },
        "orientation": "auto",
        "textMode": "name",
        "colorMode": "none",
        "graphMode": "none",
        "justifyMode": "center"
      },
      "fieldConfig": { "defaults": {}, "overrides": [] }
    },
    {
      "id": 14,
      "title": "5G Band",
      "type": "stat",
      "gridPos": { "h": 4, "w": 4, "x": 4, "y": 8 },
      "datasource": { "type": "prometheus", "uid": "cellsentry-prometheus" },
      "targets": [
        {
          "expr": "cellsentry_modem_info",
          "legendFormat": "{{band_5g}}",
          "instant": true,
          "refId": "A"
        }
      ],
      "options": {
        "reduceOptions": { "values": false, "calcs": ["lastNotNull"], "fields": "" },
        "orientation": "auto",
        "textMode": "name",
        "colorMode": "none",
        "graphMode": "none",
        "justifyMode": "center"
      },
      "fieldConfig": { "defaults": {}, "overrides": [] }
    },
    {
      "id": 15,
      "title": "5G PCI",
      "type": "stat",
      "gridPos": { "h": 4, "w": 4, "x": 8, "y": 8 },
      "datasource": { "type": "prometheus", "uid": "cellsentry-prometheus" },
      "targets": [
        {
          "expr": "cellsentry_modem_info",
          "legendFormat": "{{pci_5g}}",
          "instant": true,
          "refId": "A"
        }
      ],
      "options": {
        "reduceOptions": { "values": false, "calcs": ["lastNotNull"], "fields": "" },
        "orientation": "auto",
        "textMode": "name",
        "colorMode": "none",
        "graphMode": "none",
        "justifyMode": "center"
      },
      "fieldConfig": { "defaults": {}, "overrides": [] }
    },
    {
      "id": 7,
      "title": "LTE Signal Quality",
      "type": "timeseries",
      "gridPos": { "h": 8, "w": 24, "x": 0, "y": 16 },
      "datasource": { "type": "prometheus", "uid": "cellsentry-prometheus" },
      "targets": [
        {
          "expr": "cellsentry_lte_rsrp_dbm",
          "legendFormat": "RSRP",
          "refId": "A"
        },
        {
          "expr": "cellsentry_lte_rsrq_db",
          "legendFormat": "RSRQ",
          "refId": "B"
        },
        {
          "expr": "cellsentry_lte_snr_db",
          "legendFormat": "SNR",
          "refId": "C"
        },
        {
          "expr": "cellsentry_lte_rssi_dbm",
          "legendFormat": "RSSI",
          "refId": "D"
        }
      ],
      "options": {
        "tooltip": { "mode": "multi", "sort": "none" },
        "legend": {
          "showLegend": true,
          "displayMode": "list",
          "placement": "bottom",
          "calcs": ["lastNotNull", "min", "max"]
        }
      },
      "fieldConfig": {
        "defaults": {
          "unit": "dB",
          "custom": {
            "lineWidth": 1,
            "fillOpacity": 5,
            "gradientMode": "none",
            "spanNulls": false,
            "showPoints": "never",
            "drawStyle": "line"
          }
        },
        "overrides": [
          {
            "matcher": { "id": "byName", "options": "RSRP" },
            "properties": [
              { "id": "unit", "value": "dBm" },
              {
                "id": "thresholds",
                "value": {
                  "mode": "absolute",
                  "steps": [
                    { "color": "red",    "value": null },
                    { "color": "orange", "value": -110 },
                    { "color": "yellow", "value": -100 },
                    { "color": "green",  "value": -85 }
                  ]
                }
              },
              { "id": "custom.thresholdsStyle", "value": { "mode": "line" } }
            ]
          },
          {
            "matcher": { "id": "byName", "options": "RSSI" },
            "properties": [
              { "id": "unit", "value": "dBm" }
            ]
          }
        ]
      }
    },
    {
      "id": 8,
      "title": "5G NR Signal Quality",
      "type": "timeseries",
      "gridPos": { "h": 8, "w": 24, "x": 0, "y": 24 },
      "datasource": { "type": "prometheus", "uid": "cellsentry-prometheus" },
      "targets": [
        {
          "expr": "cellsentry_5gnr_rsrp_dbm",
          "legendFormat": "NR RSRP",
          "refId": "A"
        },
        {
          "expr": "cellsentry_5gnr_rsrq_db",
          "legendFormat": "NR RSRQ",
          "refId": "B"
        },
        {
          "expr": "cellsentry_5gnr_sinr_db",
          "legendFormat": "NR SINR",
          "refId": "C"
        }
      ],
      "options": {
        "tooltip": { "mode": "multi", "sort": "none" },
        "legend": {
          "showLegend": true,
          "displayMode": "list",
          "placement": "bottom",
          "calcs": ["lastNotNull", "min", "max"]
        }
      },
      "fieldConfig": {
        "defaults": {
          "unit": "dB",
          "custom": {
            "lineWidth": 1,
            "fillOpacity": 5,
            "gradientMode": "none",
            "spanNulls": false,
            "showPoints": "never",
            "drawStyle": "line"
          }
        },
        "overrides": [
          {
            "matcher": { "id": "byName", "options": "NR RSRP" },
            "properties": [
              { "id": "unit", "value": "dBm" },
              {
                "id": "thresholds",
                "value": {
                  "mode": "absolute",
                  "steps": [
                    { "color": "red",    "value": null },
                    { "color": "orange", "value": -110 },
                    { "color": "yellow", "value": -100 },
                    { "color": "green",  "value": -85 }
                  ]
                }
              },
              { "id": "custom.thresholdsStyle", "value": { "mode": "line" } }
            ]
          }
        ]
      }
    },
    {
      "id": 9,
      "title": "Throughput",
      "type": "timeseries",
      "gridPos": { "h": 8, "w": 24, "x": 0, "y": 32 },
      "datasource": { "type": "prometheus", "uid": "cellsentry-prometheus" },
      "targets": [
        {
          "expr": "cellsentry_throughput_bps{direction=\"rx\"}",
          "legendFormat": "Download",
          "refId": "A"
        },
        {
          "expr": "cellsentry_throughput_bps{direction=\"tx\"}",
          "legendFormat": "Upload",
          "refId": "B"
        }
      ],
      "options": {
        "tooltip": { "mode": "multi", "sort": "none" },
        "legend": {
          "showLegend": true,
          "displayMode": "list",
          "placement": "bottom",
          "calcs": ["lastNotNull", "max"]
        }
      },
      "fieldConfig": {
        "defaults": {
          "unit": "bps",
          "custom": {
            "lineWidth": 1,
            "fillOpacity": 10,
            "gradientMode": "none",
            "spanNulls": false,
            "showPoints": "never",
            "drawStyle": "line"
          }
        },
        "overrides": []
      }
    }
  ],
  "refresh": "30s",
  "schemaVersion": 39,
  "tags": ["cellsentry", "5g", "lte"],
  "time": { "from": "now-3h", "to": "now" },
  "timepicker": {},
  "timezone": "browser",
  "title": "CellSentry \u2014 ZTE MC801A Signal Monitor",
  "uid": "cellsentry-v1",
  "version": 1
}
